nomad_camels_driver_pi_stage_e709/__init__.py
nomad_camels_driver_pi_stage_e709/pi_stage_e709.py
nomad_camels_driver_pi_stage_e709/pi_stage_e709_ophyd.py
nomad_camels_driver_pi_stage_e709-0.1.1.dist-info/LICENSE.txt
nomad_camels_driver_pi_stage_e709-0.1.1.dist-info/METADATA
nomad_camels_driver_pi_stage_e709-0.1.1.dist-info/WHEEL
nomad_camels_driver_pi_stage_e709-0.1.1.dist-info/top_level.txt
nomad_camels_driver_pi_stage_e709-0.1.1.dist-info/RECORD
