Metadata-Version: 2.1
Name: nomad-camels-driver-pi-stage-e709
Version: 0.1.1
Summary: Instrument driver for PI E709 piezo stage for NOMAD-CAMELS
Author-email: FAIRmat - HU Berlin <nomad-camels@fau.de>
Project-URL: GitHub Page, https://github.com/FAU-LAP/NOMAD-CAMELS
Project-URL: GitHub Drivers, https://github.com/FAU-LAP/CAMELS_drivers
Project-URL: Documentation, https://fau-lap.github.io/NOMAD-CAMELS/doc/instruments/instruments.html
Classifier: Programming Language :: Python :: 3
Classifier: License :: OSI Approved :: GNU Lesser General Public License v2 (LGPLv2)
Requires-Python: >=3.9.6
License-File: LICENSE.txt
Requires-Dist: PIPython
Requires-Dist: nomad-camels
